{
  "TesseractFra-PNG-jspll-ELTeC": [
    "Biblioth\u00e8que nationale de France 11_INCONNU_Poesies-diverses",
    "Portrait de Mademoiflle + X_INCONNU_Poesies-diverses",
    "N A\u00c2ATIER_INCONNU_Poesies-diverses",
    "Modele_INCONNU_Poesies-diverses",
    "Paris_INCONNU_Poesies-diverses",
    "Saifons_INCONNU_Poesies-diverses",
    "Balance_INCONNU_Poesies-diverses",
    "Baifers_INCONNU_Poesies-diverses",
    "Etrennes_INCONNU_Poesies-diverses",
    "CLOQUET_INCONNU_Poesies-diverses",
    "Est_INCONNU_Poesies-diverses",
    "MADEMOQOISELLE_INCONNU_Poesies-diverses",
    "MADRIGAL_INCONNU_Poesies-diverses",
    "Pres_INCONNU_Poesies-diverses",
    "Belles_INCONNU_Poesies-diverses",
    "Amans_INCONNU_Poesies-diverses",
    "SI_INCONNU_Poesies-diverses",
    "Limites_INCONNU_Poesies-diverses",
    "Egl\u00e9_INCONNU_Poesies-diverses",
    "PAn_INCONNU_Poesies-diverses",
    "Plume_INCONNU_Poesies-diverses",
    "\u00d9 Printems_INCONNU_Poesies-diverses",
    "Luy_INCONNU_Poesies-diverses",
    "Vallon_INCONNU_Poesies-diverses",
    "Mars_INCONNU_Poesies-diverses",
    "Line NAN \u00c9 usIne_INCONNU_Poesies-diverses"
  ],
  "TesseractFra-PNG-jspll-pretrain": [
    "Biblioth\u00e8que nationale de France_INCONNU_Poesies-diverses",
    "MpoDIVERSES_INCONNU_Poesies-diverses",
    "Web\u00e9_INCONNU_Poesies-diverses",
    "3\u00b0 J_INCONNU_Poesies-diverses",
    "Modele_INCONNU_Poesies-diverses",
    "MADEMOISELLE E_INCONNU_Poesies-diverses",
    "Kk_INCONNU_Poesies-diverses",
    "Paris_INCONNU_Poesies-diverses",
    "AL_INCONNU_Poesies-diverses",
    "Balance_INCONNU_Poesies-diverses",
    "Est_INCONNU_Poesies-diverses",
    "Pin\u00e7eau_INCONNU_Poesies-diverses",
    "Pres_INCONNU_Poesies-diverses",
    "Belles_INCONNU_Poesies-diverses",
    "Amans_INCONNU_Poesies-diverses",
    "SI_INCONNU_Poesies-diverses",
    "Limites_INCONNU_Poesies-diverses",
    "A 6 EN RE_INCONNU_Poesies-diverses",
    "PAn_INCONNU_Poesies-diverses",
    "Plume_INCONNU_Poesies-diverses",
    "Apanage_INCONNU_Poesies-diverses",
    "Mars_INCONNU_Poesies-diverses",
    "MARVILLE_INCONNU_Poesies-diverses",
    "Line NAN \u00c9_INCONNU_Poesies-diverses"
  ],
  "TesseractFra-png": [
    "Biblioth\u00e8que nationale de France_INCONNU_Poesies-diverses",
    "MpoDIVERSES_INCONNU_Poesies-diverses",
    "Portrait de Mademoiflle + X_INCONNU_Poesies-diverses",
    "N A\u00c2ATIER_INCONNU_Poesies-diverses",
    "Modele_INCONNU_Poesies-diverses",
    "Kk_INCONNU_Poesies-diverses",
    "Paris_INCONNU_Poesies-diverses",
    "Saifons_INCONNU_Poesies-diverses",
    "Balance_INCONNU_Poesies-diverses",
    "Puifqu_INCONNU_Poesies-diverses",
    "Baifers_INCONNU_Poesies-diverses",
    "Etrennes_INCONNU_Poesies-diverses",
    "MADEMOQOISELLE_INCONNU_Poesies-diverses",
    "MADRIGAL_INCONNU_Poesies-diverses",
    "Eviens_INCONNU_Poesies-diverses",
    "Egl\u00e9_INCONNU_Poesies-diverses",
    "Ctoy_INCONNU_Poesies-diverses",
    "O_INCONNU_Poesies-diverses",
    "Pres_INCONNU_Poesies-diverses",
    "Belles_INCONNU_Poesies-diverses",
    "Amans_INCONNU_Poesies-diverses",
    "SI_INCONNU_Poesies-diverses",
    "Limites_INCONNU_Poesies-diverses",
    "Egl\u00e9_INCONNU_Poesies-diverses",
    "PAn_INCONNU_Poesies-diverses",
    "Plume_INCONNU_Poesies-diverses",
    "Du_INCONNU_Poesies-diverses",
    "\u00d9 Printems_INCONNU_Poesies-diverses",
    "Luy_INCONNU_Poesies-diverses",
    "Vallon_INCONNU_Poesies-diverses",
    "Mars_INCONNU_Poesies-diverses",
    "Line NAN \u00c9_INCONNU_Poesies-diverses"
  ],
  "kraken-jspll-ELTeC": [
    "CI0QUERIC_INCONNU_Poesies-diverses",
    "AUXTARFS_INCONNU_Poesies-diverses",
    "Lutilisateur_INCONNU_Poesies-diverses",
    "M A D A M E T_INCONNU_Poesies-diverses",
    "ailas h sgee_INCONNU_Poesies-diverses",
    "Jupiter_INCONNU_Poesies-diverses",
    "metre_INCONNU_Poesies-diverses",
    "Balanee_INCONNU_Poesies-diverses",
    "D_INCONNU_Poesies-diverses",
    "Etrennes_INCONNU_Poesies-diverses",
    "D.AIME_INCONNU_Poesies-diverses",
    "E_INCONNU_Poesies-diverses",
    "Motifs_INCONNU_Poesies-diverses",
    "el-l_INCONNU_Poesies-diverses",
    "fiifint_INCONNU_Poesies-diverses",
    "Tableu_INCONNU_Poesies-diverses",
    "Nom jufqu'_INCONNU_Poesies-diverses",
    "laie.1 MAD R IGAL_INCONNU_Poesies-diverses",
    "Pleusss maiS_INCONNU_Poesies-diverses",
    "5 O_INCONNU_Poesies-diverses",
    "penfe_INCONNU_Poesies-diverses",
    "P_INCONNU_Poesies-diverses",
    "E_INCONNU_Poesies-diverses",
    "Cythee_INCONNU_Poesies-diverses",
    "sOuveNT_INCONNU_Poesies-diverses",
    "A_INCONNU_Poesies-diverses",
    "precher_INCONNU_Poesies-diverses",
    "Belles_INCONNU_Poesies-diverses",
    "Amans_INCONNU_Poesies-diverses",
    "Egle_INCONNU_Poesies-diverses",
    "O_INCONNU_Poesies-diverses",
    "pemier_INCONNU_Poesies-diverses",
    "Plume_INCONNU_Poesies-diverses",
    "Appanege_INCONNU_Poesies-diverses",
    "entralner_INCONNU_Poesies-diverses",
    "Portrai_INCONNU_Poesies-diverses",
    "Luy_INCONNU_Poesies-diverses",
    "cr Vallon_INCONNU_Poesies-diverses"
  ],
  "kraken-jspll-pretrain": [
    "CLI0QUERIC_INCONNU_Poesies-diverses",
    "Lutilisateur_INCONNU_Poesies-diverses",
    "I_INCONNU_Poesies-diverses",
    "Jupiter_INCONNU_Poesies-diverses",
    "Paris_INCONNU_Poesies-diverses",
    "Ei_INCONNU_Poesies-diverses",
    "inde_INCONNU_Poesies-diverses",
    "Balance_INCONNU_Poesies-diverses",
    "D_INCONNU_Poesies-diverses",
    "Motifs_INCONNU_Poesies-diverses",
    "el-l tout fon_INCONNU_Poesies-diverses",
    "S ME pres_INCONNU_Poesies-diverses",
    "laie.1 MAD R GAL_INCONNU_Poesies-diverses",
    "A_INCONNU_Poesies-diverses",
    "Pieuses_INCONNU_Poesies-diverses",
    "P_INCONNU_Poesies-diverses",
    "E_INCONNU_Poesies-diverses",
    "Cythee_INCONNU_Poesies-diverses",
    "precher_INCONNU_Poesies-diverses",
    "Belles_INCONNU_Poesies-diverses",
    "Amans_INCONNU_Poesies-diverses",
    "Limites_INCONNU_Poesies-diverses",
    "O_INCONNU_Poesies-diverses",
    "L D'aller visiter des Amis_INCONNU_Poesies-diverses",
    "Plume_INCONNU_Poesies-diverses",
    "aiakhhgge_INCONNU_Poesies-diverses",
    "Apanage_INCONNU_Poesies-diverses",
    "olsen fi_INCONNU_Poesies-diverses",
    "Coeur_INCONNU_Poesies-diverses",
    "E_INCONNU_Poesies-diverses",
    "terie_INCONNU_Poesies-diverses",
    "Pt e'_INCONNU_Poesies-diverses",
    "Luy_INCONNU_Poesies-diverses",
    "cr Vallon_INCONNU_Poesies-diverses",
    "S IL_INCONNU_Poesies-diverses"
  ],
  "kraken": [
    "CLI0QUERIC_INCONNU_Poesies-diverses",
    "AUXTARFS_INCONNU_Poesies-diverses",
    "Lutilisateur_INCONNU_Poesies-diverses",
    "I_INCONNU_Poesies-diverses",
    "ailas h sgee_INCONNU_Poesies-diverses",
    "Jupiter_INCONNU_Poesies-diverses",
    "metre_INCONNU_Poesies-diverses",
    "Molele_INCONNU_Poesies-diverses",
    "Balanee_INCONNU_Poesies-diverses",
    "Puifqu'_INCONNU_Poesies-diverses",
    "D_INCONNU_Poesies-diverses",
    "Etrennes_INCONNU_Poesies-diverses",
    "Motifs_INCONNU_Poesies-diverses",
    "el-l_INCONNU_Poesies-diverses",
    "fiifint_INCONNU_Poesies-diverses",
    "Tableu_INCONNU_Poesies-diverses",
    "Nom jufqu'_INCONNU_Poesies-diverses",
    "S ME pres_INCONNU_Poesies-diverses",
    "laie.1 MAD R IGAL_INCONNU_Poesies-diverses",
    "Egle_INCONNU_Poesies-diverses",
    "penfe_INCONNU_Poesies-diverses",
    "P_INCONNU_Poesies-diverses",
    "E_INCONNU_Poesies-diverses",
    "Cythee_INCONNU_Poesies-diverses",
    "precher_INCONNU_Poesies-diverses",
    "Belles_INCONNU_Poesies-diverses",
    "Amans_INCONNU_Poesies-diverses",
    "Egle_INCONNU_Poesies-diverses",
    "O_INCONNU_Poesies-diverses",
    "pemier_INCONNU_Poesies-diverses",
    "Plume_INCONNU_Poesies-diverses",
    "Appanege_INCONNU_Poesies-diverses",
    "entralner_INCONNU_Poesies-diverses",
    "Portrai_INCONNU_Poesies-diverses",
    "Pt e'y erende_INCONNU_Poesies-diverses",
    "Luy_INCONNU_Poesies-diverses",
    "cr Vallon_INCONNU_Poesies-diverses"
  ],
  "Ref": [
    "Sagei\u00ef\u00e8_INCONNU_Poesies-diverses",
    "Jupiter_INCONNU_Poesies-diverses",
    "MADRIGAL_INCONNU_Poesies-diverses",
    "Prmt\u00e8ms_INCONNU_Poesies-diverses",
    "PEte_INCONNU_Poesies-diverses",
    "ElMl_INCONNU_Poesies-diverses",
    "f\u00e7ay_INCONNU_Poesies-diverses",
    "Etrennes_INCONNU_Poesies-diverses",
    "m_INCONNU_Poesies-diverses",
    "N_INCONNU_Poesies-diverses",
    "Peintre_INCONNU_Poesies-diverses",
    "Tableau_INCONNU_Poesies-diverses",
    "Hfais_INCONNU_Poesies-diverses",
    "f\u00e7ay_INCONNU_Poesies-diverses",
    "E_INCONNU_Poesies-diverses",
    "Egl\u00e9_INCONNU_Poesies-diverses",
    "MADRIGAL_INCONNU_Poesies-diverses",
    "A_INCONNU_Poesies-diverses",
    "MADRIGAL_INCONNU_Poesies-diverses",
    "\u00eeongtems_INCONNU_Poesies-diverses",
    "Belles_INCONNU_Poesies-diverses",
    "Amans_INCONNU_Poesies-diverses",
    "E sr_INCONNU_Poesies-diverses",
    "Egl\u00e9_INCONNU_Poesies-diverses",
    "Plume_INCONNU_Poesies-diverses",
    "Vallon 9^' En vain_INCONNU_Poesies-diverses",
    "puifque_INCONNU_Poesies-diverses",
    "M_INCONNU_Poesies-diverses",
    "LraeJ$c^af8J_INCONNU_Poesies-diverses"
  ]
}